mkdocs_bootswatch_classic/__init__.py
mkdocs_bootswatch_classic/amelia/__init__.py
mkdocs_bootswatch_classic/amelia/mkdocs_theme.yml
mkdocs_bootswatch_classic/amelia/css/base.css
mkdocs_bootswatch_classic/amelia/css/bootstrap-custom.min.css
mkdocs_bootswatch_classic/bootstrap/__init__.py
mkdocs_bootswatch_classic/bootstrap/main.html
mkdocs_bootswatch_classic/bootstrap/mkdocs_theme.yml
mkdocs_bootswatch_classic/bootstrap/css/base.css
mkdocs_bootswatch_classic/bootstrap/css/bootstrap-3.3.7.min.css
mkdocs_bootswatch_classic/bootstrap/js/bootstrap-3.3.7.min.js
mkdocs_bootswatch_classic/cerulean/__init__.py
mkdocs_bootswatch_classic/cerulean/mkdocs_theme.yml
mkdocs_bootswatch_classic/cerulean/css/base.css
mkdocs_bootswatch_classic/cerulean/css/bootstrap-custom.min.css
mkdocs_bootswatch_classic/cosmo/__init__.py
mkdocs_bootswatch_classic/cosmo/mkdocs_theme.yml
mkdocs_bootswatch_classic/cosmo/css/base.css
mkdocs_bootswatch_classic/cosmo/css/bootstrap-custom.min.css
mkdocs_bootswatch_classic/cyborg/__init__.py
mkdocs_bootswatch_classic/cyborg/mkdocs_theme.yml
mkdocs_bootswatch_classic/cyborg/css/base.css
mkdocs_bootswatch_classic/cyborg/css/bootstrap-custom.min.css
mkdocs_bootswatch_classic/flatly/__init__.py
mkdocs_bootswatch_classic/flatly/mkdocs_theme.yml
mkdocs_bootswatch_classic/flatly/css/base.css
mkdocs_bootswatch_classic/flatly/css/bootstrap-custom.min.css
mkdocs_bootswatch_classic/journal/__init__.py
mkdocs_bootswatch_classic/journal/mkdocs_theme.yml
mkdocs_bootswatch_classic/journal/css/base.css
mkdocs_bootswatch_classic/journal/css/bootstrap-custom.min.css
mkdocs_bootswatch_classic/mkdocs/404.html
mkdocs_bootswatch_classic/mkdocs/__init__.py
mkdocs_bootswatch_classic/mkdocs/base.html
mkdocs_bootswatch_classic/mkdocs/content.html
mkdocs_bootswatch_classic/mkdocs/keyboard-modal.html
mkdocs_bootswatch_classic/mkdocs/main.html
mkdocs_bootswatch_classic/mkdocs/mkdocs_theme.yml
mkdocs_bootswatch_classic/mkdocs/nav-sub.html
mkdocs_bootswatch_classic-1.0.dist-info/LICENSE
mkdocs_bootswatch_classic-1.0.dist-info/METADATA
mkdocs_bootswatch_classic-1.0.dist-info/WHEEL
mkdocs_bootswatch_classic-1.0.dist-info/entry_points.txt
mkdocs_bootswatch_classic-1.0.dist-info/top_level.txt
mkdocs_bootswatch_classic-1.0.dist-info/RECORD
