Metadata-Version: 2.1
Name: mkdocs-bootswatch-classic
Version: 1.0
Summary: Bootswatch themes for MkDocs
Home-page: http://www.mkdocs.org
Author: Dougal Matthews
Author-email: dougal@dougalmatthews.com
License: BSD
Platform: UNKNOWN
Requires-Python: >=2.7.9,!=3.0.*,!=3.1.*,!=3.2.*,!=3.3.*
Requires-Dist: mkdocs (>=1.0)
